pardos/__init__.py
pardos/methods.py
pardos/register.py
pardos/times.py
pardos/unix.py
pardos-0.0.1.dist-info/LICENSE
pardos-0.0.1.dist-info/METADATA
pardos-0.0.1.dist-info/WHEEL
pardos-0.0.1.dist-info/top_level.txt
pardos-0.0.1.dist-info/RECORD
